clime_metrics/__init__.py
clime_metrics/main.py
clime_metrics/version.py
clime_metrics-0.9.3.dist-info/LICENSE
clime_metrics-0.9.3.dist-info/METADATA
clime_metrics-0.9.3.dist-info/WHEEL
clime_metrics-0.9.3.dist-info/top_level.txt
clime_metrics-0.9.3.dist-info/RECORD
